setup.py
hertx/__init__.py
hertx/excel.py
hertx/httpx.py
hertx/m3u8.py
hertx/mysql.py
hertx/pdf.py
hertx/redis.py
hertx/video.py
hertx/win32.py
hertx/word.py
hertx.egg-info/PKG-INFO
hertx.egg-info/SOURCES.txt
hertx.egg-info/dependency_links.txt
hertx.egg-info/requires.txt
hertx.egg-info/top_level.txt