Metadata-Version: 1.0
Name: hertx
Version: 1.0.4
Summary: 这是一个工具集合包
Home-page: UNKNOWN
Author: hxq
Author-email: 337168530@qq.com
License: GPL
Platform: UNKNOWN
